secure_gen_tk/__init__.py
secure_gen_tk/app.py
secure_gen_tk/generator.py
secure_gen_tk-0.1.2.dist-info/METADATA
secure_gen_tk-0.1.2.dist-info/WHEEL
secure_gen_tk-0.1.2.dist-info/entry_points.txt
secure_gen_tk-0.1.2.dist-info/top_level.txt
secure_gen_tk-0.1.2.dist-info/RECORD
