Metadata-Version: 2.4
Name: secure-gen-tk
Version: 0.1.2
Summary: Генератор паролей с графическим интерфейсом на tkinter
Author: ALohaV2
Author-email: pyutilsverif@gmail.com
Requires-Python: >=3.7
Dynamic: author
Dynamic: author-email
Dynamic: requires-python
Dynamic: summary
